himpunan/__init__.py
himpunan/himpunan.py
python_himpunan-0.1.1.dist-info/METADATA
python_himpunan-0.1.1.dist-info/WHEEL
python_himpunan-0.1.1.dist-info/top_level.txt
python_himpunan-0.1.1.dist-info/RECORD
