Metadata-Version: 2.1
Name: python-himpunan
Version: 0.1.1
Summary: Library Himpunan sederhana menggunakan Python
Home-page: https://github.com/KingPublic/python-himpunan-klp9/tree/main
Author: Andreyhs
Author-email: ahartawan01@gmail.com
Classifier: Programming Language :: Python :: 3
Classifier: License :: OSI Approved :: MIT License
Classifier: Operating System :: OS Independent
Requires-Python: >=3.6
